[
  {
    "id": "prod_001",
    "brand": "Cantu",
    "name": "Shea Butter Sulfate-Free Cleansing Cream Shampoo",
    "type": "shampoo",
    "category": "shampoo",
    "description": "Gently removes heavy buildup. Ideal for natural hair.",
    "ingredients": [
      {
        "name": "Aqua (Water)",
        "purpose": "Solvent",
        "effect": "Hydrates and dissolves other ingredients"
      },
      {
        "name": "Sodium C14-16 Olefin Sulfonate",
        "purpose": "Surfactant",
        "effect": "Cleanses by helping water to mix with oil and dirt so they can be rinsed away"
      },
      {
        "name": "Cocamidopropyl Betaine",
        "purpose": "Surfactant",
        "effect": "Mild cleanser derived from coconut oil"
      },
      {
        "name": "Glycol Distearate",
        "purpose": "Opacifier",
        "effect": "Adds pearlescent appearance and thickens the product"
      },
      {
        "name": "Panthenol",
        "purpose": "Pro-vitamin B5",
        "effect": "Improves hair elasticity, moisture retention, and flexibility"
      },
      {
        "name": "Tocopheryl Acetate (Vitamin E)",
        "purpose": "Antioxidant",
        "effect": "Protects hair and skin cells from damage"
      },
      {
        "name": "Polyquaternium-10",
        "purpose": "Film-forming agent",
        "effect": "Reduces static and smoothens hair"
      },
      {
        "name": "Fragrance (Parfum)",
        "purpose": "Scent",
        "effect": "Adds a pleasant fragrance"
      },
      {
        "name": "Citric Acid",
        "purpose": "pH Adjuster",
        "effect": "Balances the acidity of the product"
      },
      {
        "name": "Disodium EDTA",
        "purpose": "Chelating Agent",
        "effect": "Stabilizes formula by binding to metal ions"
      }
    ],
    "suitableHairTypes": ["3A", "3B", "3C", "4A", "4B", "4C"],
    "price": 8.99,
    "size": "13.5 fl oz (400 ml)",
    "barcode": "817513015311",
    "imageUrl": "https://example.com/cantu-shampoo.jpg",
    "isCustom": false,
    "sulfateFree": true,
    "siliconeFree": true,
    "crueltyFree": true,
    "coilyHairFriendly": true,
    "createdAt": "2024-01-01T00:00:00Z",
    "updatedAt": "2024-01-01T00:00:00Z"
  },
  {
    "id": "prod_002",
    "brand": "Brand2",
    "name": "Product 2 Name",
    "type": "conditioner",
    "category": "conditioner",
    "description": "Restorative formula for hydration and strength. Product 2 edition.",
    "ingredients": [
      {
        "name": "Aqua (Water)",
        "purpose": "Solvent",
        "effect": "Hydrates"
      },
      {
        "name": "Cetearyl Alcohol",
        "purpose": "Emollient",
        "effect": "Softens hair"
      },
      {
        "name": "Shea Butter",
        "purpose": "Moisturizer",
        "effect": "Adds intense moisture"
      },
      {
        "name": "Argan Oil",
        "purpose": "Nourishment",
        "effect": "Improves shine and softness"
      },
      {
        "name": "Fragrance",
        "purpose": "Scent",
        "effect": "Adds pleasant smell"
      }
    ],
    "suitableHairTypes": ["2A", "2B", "2C", "3A", "3B", "3C"],
    "price": 12.99,
    "size": "12 fl oz",
    "barcode": "80000000002",
    "imageUrl": "https://example.com/product2.jpg",
    "isCustom": false,
    "sulfateFree": true,
    "siliconeFree": true,
    "crueltyFree": true,
    "coilyHairFriendly": true,
    "createdAt": "2024-01-01T00:00:00Z",
    "updatedAt": "2024-01-01T00:00:00Z"
  },
  {
    "id": "prod_003",
    "brand": "Brand3",
    "name": "Product 3 Name",
    "type": "oil",
    "category": "oil",
    "description": "Restorative formula for hydration and strength. Product 3 edition.",
    "ingredients": [
      {
        "name": "Aqua (Water)",
        "purpose": "Solvent",
        "effect": "Hydrates"
      },
      {
        "name": "Cetearyl Alcohol",
        "purpose": "Emollient",
        "effect": "Softens hair"
      },
      {
        "name": "Shea Butter",
        "purpose": "Moisturizer",
        "effect": "Adds intense moisture"
      },
      {
        "name": "Argan Oil",
        "purpose": "Nourishment",
        "effect": "Improves shine and softness"
      },
      {
        "name": "Fragrance",
        "purpose": "Scent",
        "effect": "Adds pleasant smell"
      }
    ],
    "suitableHairTypes": ["3A", "3B", "3C", "4A", "4B", "4C"],
    "price": 15.99,
    "size": "12 fl oz",
    "barcode": "80000000003",
    "imageUrl": "https://example.com/product3.jpg",
    "isCustom": false,
    "sulfateFree": true,
    "siliconeFree": false,
    "crueltyFree": true,
    "coilyHairFriendly": true,
    "createdAt": "2024-01-01T00:00:00Z",
    "updatedAt": "2024-01-01T00:00:00Z"
  },
  {
    "id": "prod_004",
    "brand": "Brand4",
    "name": "Product 4 Name",
    "type": "Conditioner",
    "size": "12 fl oz",
    "barcode": "80000000004",
    "for": "Dry, Damaged Hair",
    "description": "Restorative formula for hydration and strength. Product 4 edition.",
    "sulfate_free": true,
    "silicone_free": true,
    "cruelty_free": true,
    "made_in": "USA",
    "ingredients": [
      {
        "name": "Aqua (Water)",
        "purpose": "Solvent",
        "effect": "Hydrates"
      },
      {
        "name": "Cetearyl Alcohol",
        "purpose": "Emollient",
        "effect": "Softens hair"
      },
      {
        "name": "Shea Butter",
        "purpose": "Moisturizer",
        "effect": "Adds intense moisture"
      },
      {
        "name": "Argan Oil",
        "purpose": "Nourishment",
        "effect": "Improves shine and softness"
      },
      {
        "name": "Fragrance",
        "purpose": "Scent",
        "effect": "Adds pleasant smell"
      }
    ],
    "suggestedFor": {
      "hairGoals": {
        "Longer": true,
        "Healthier": true,
        "Defined curls": false,
        "Protective styling": false,
        "Edge growth": false,
        "All of the above": false
      },
      "porosity": {
        "High": true,
        "Mid": true,
        "Low": false
      },
      "routine": {
        "Daily": false,
        "Weekly": true,
        "During protective style": false
      }
    }
  },
  {
    "id": "prod_005",
    "brand": "Brand5",
    "name": "Product 5 Name",
    "type": "Oil",
    "size": "12 fl oz",
    "barcode": "80000000005",
    "for": "Dry, Damaged Hair",
    "description": "Restorative formula for hydration and strength. Product 5 edition.",
    "sulfate_free": true,
    "silicone_free": false,
    "cruelty_free": true,
    "made_in": "USA",
    "ingredients": [
      {
        "name": "Aqua (Water)",
        "purpose": "Solvent",
        "effect": "Hydrates"
      },
      {
        "name": "Cetearyl Alcohol",
        "purpose": "Emollient",
        "effect": "Softens hair"
      },
      {
        "name": "Shea Butter",
        "purpose": "Moisturizer",
        "effect": "Adds intense moisture"
      },
      {
        "name": "Argan Oil",
        "purpose": "Nourishment",
        "effect": "Improves shine and softness"
      },
      {
        "name": "Fragrance",
        "purpose": "Scent",
        "effect": "Adds pleasant smell"
      }
    ],
    "suggestedFor": {
      "hairGoals": {
        "Longer": false,
        "Healthier": true,
        "Defined curls": false,
        "Protective styling": true,
        "Edge growth": false,
        "All of the above": false
      },
      "porosity": {
        "High": true,
        "Mid": false,
        "Low": true
      },
      "routine": {
        "Daily": false,
        "Weekly": true,
        "During protective style": true
      }
    }
  },
  {
    "id": "prod_006",
    "brand": "Brand6",
    "name": "Product 6 Name",
    "type": "Conditioner",
    "size": "12 fl oz",
    "barcode": "80000000006",
    "for": "Dry, Damaged Hair",
    "description": "Restorative formula for hydration and strength. Product 6 edition.",
    "sulfate_free": true,
    "silicone_free": true,
    "cruelty_free": true,
    "made_in": "USA",
    "ingredients": [
      {
        "name": "Aqua (Water)",
        "purpose": "Solvent",
        "effect": "Hydrates"
      },
      {
        "name": "Cetearyl Alcohol",
        "purpose": "Emollient",
        "effect": "Softens hair"
      },
      {
        "name": "Shea Butter",
        "purpose": "Moisturizer",
        "effect": "Adds intense moisture"
      },
      {
        "name": "Argan Oil",
        "purpose": "Nourishment",
        "effect": "Improves shine and softness"
      },
      {
        "name": "Fragrance",
        "purpose": "Scent",
        "effect": "Adds pleasant smell"
      }
    ],
    "suggestedFor": {
      "hairGoals": {
        "Longer": true,
        "Healthier": true,
        "Defined curls": true,
        "Protective styling": false,
        "Edge growth": false,
        "All of the above": true
      },
      "porosity": {
        "High": true,
        "Mid": true,
        "Low": false
      },
      "routine": {
        "Daily": true,
        "Weekly": true,
        "During protective style": false
      }
    }
  },
  {
    "id": "prod_007",
    "brand": "Brand7",
    "name": "Product 7 Name",
    "type": "Oil",
    "size": "12 fl oz",
    "barcode": "80000000007",
    "for": "Dry, Damaged Hair",
    "description": "Restorative formula for hydration and strength. Product 7 edition.",
    "sulfate_free": true,
    "silicone_free": false,
    "cruelty_free": true,
    "made_in": "USA",
    "ingredients": [
      {
        "name": "Aqua (Water)",
        "purpose": "Solvent",
        "effect": "Hydrates"
      },
      {
        "name": "Cetearyl Alcohol",
        "purpose": "Emollient",
        "effect": "Softens hair"
      },
      {
        "name": "Shea Butter",
        "purpose": "Moisturizer",
        "effect": "Adds intense moisture"
      },
      {
        "name": "Argan Oil",
        "purpose": "Nourishment",
        "effect": "Improves shine and softness"
      },
      {
        "name": "Fragrance",
        "purpose": "Scent",
        "effect": "Adds pleasant smell"
      }
    ],
    "suggestedFor": {
      "hairGoals": {
        "Longer": false,
        "Healthier": true,
        "Defined curls": false,
        "Protective styling": true,
        "Edge growth": false,
        "All of the above": false
      },
      "porosity": {
        "High": true,
        "Mid": false,
        "Low": true
      },
      "routine": {
        "Daily": false,
        "Weekly": true,
        "During protective style": true
      }
    }
  },
  {
    "id": "prod_008",
    "brand": "Brand8",
    "name": "Product 8 Name",
    "type": "Conditioner",
    "size": "12 fl oz",
    "barcode": "80000000008",
    "for": "Dry, Damaged Hair",
    "description": "Restorative formula for hydration and strength. Product 8 edition.",
    "sulfate_free": true,
    "silicone_free": true,
    "cruelty_free": true,
    "made_in": "USA",
    "ingredients": [
      {
        "name": "Aqua (Water)",
        "purpose": "Solvent",
        "effect": "Hydrates"
      },
      {
        "name": "Cetearyl Alcohol",
        "purpose": "Emollient",
        "effect": "Softens hair"
      },
      {
        "name": "Shea Butter",
        "purpose": "Moisturizer",
        "effect": "Adds intense moisture"
      },
      {
        "name": "Argan Oil",
        "purpose": "Nourishment",
        "effect": "Improves shine and softness"
      },
      {
        "name": "Fragrance",
        "purpose": "Scent",
        "effect": "Adds pleasant smell"
      }
    ],
    "suggestedFor": {
      "hairGoals": {
        "Longer": true,
        "Healthier": true,
        "Defined curls": false,
        "Protective styling": false,
        "Edge growth": false,
        "All of the above": false
      },
      "porosity": {
        "High": true,
        "Mid": true,
        "Low": false
      },
      "routine": {
        "Daily": false,
        "Weekly": true,
        "During protective style": false
      }
    }
  },
  {
    "id": "prod_009",
    "brand": "Brand9",
    "name": "Product 9 Name",
    "type": "Oil",
    "size": "12 fl oz",
    "barcode": "80000000009",
    "for": "Dry, Damaged Hair",
    "description": "Restorative formula for hydration and strength. Product 9 edition.",
    "sulfate_free": true,
    "silicone_free": false,
    "cruelty_free": true,
    "made_in": "USA",
    "ingredients": [
      {
        "name": "Aqua (Water)",
        "purpose": "Solvent",
        "effect": "Hydrates"
      },
      {
        "name": "Cetearyl Alcohol",
        "purpose": "Emollient",
        "effect": "Softens hair"
      },
      {
        "name": "Shea Butter",
        "purpose": "Moisturizer",
        "effect": "Adds intense moisture"
      },
      {
        "name": "Argan Oil",
        "purpose": "Nourishment",
        "effect": "Improves shine and softness"
      },
      {
        "name": "Fragrance",
        "purpose": "Scent",
        "effect": "Adds pleasant smell"
      }
    ],
    "suggestedFor": {
      "hairGoals": {
        "Longer": false,
        "Healthier": true,
        "Defined curls": true,
        "Protective styling": true,
        "Edge growth": false,
        "All of the above": true
      },
      "porosity": {
        "High": true,
        "Mid": false,
        "Low": true
      },
      "routine": {
        "Daily": true,
        "Weekly": true,
        "During protective style": true
      }
    }
  },
  {
    "id": "prod_0010",
    "brand": "Brand10",
    "name": "Product 10 Name",
    "type": "Conditioner",
    "size": "12 fl oz",
    "barcode": "800000000010",
    "for": "Dry, Damaged Hair",
    "description": "Restorative formula for hydration and strength. Product 10 edition.",
    "sulfate_free": true,
    "silicone_free": true,
    "cruelty_free": true,
    "made_in": "USA",
    "ingredients": [
      {
        "name": "Aqua (Water)",
        "purpose": "Solvent",
        "effect": "Hydrates"
      },
      {
        "name": "Cetearyl Alcohol",
        "purpose": "Emollient",
        "effect": "Softens hair"
      },
      {
        "name": "Shea Butter",
        "purpose": "Moisturizer",
        "effect": "Adds intense moisture"
      },
      {
        "name": "Argan Oil",
        "purpose": "Nourishment",
        "effect": "Improves shine and softness"
      },
      {
        "name": "Fragrance",
        "purpose": "Scent",
        "effect": "Adds pleasant smell"
      }
    ],
    "suggestedFor": {
      "hairGoals": {
        "Longer": true,
        "Healthier": true,
        "Defined curls": false,
        "Protective styling": false,
        "Edge growth": false,
        "All of the above": false
      },
      "porosity": {
        "High": true,
        "Mid": true,
        "Low": false
      },
      "routine": {
        "Daily": false,
        "Weekly": true,
        "During protective style": false
      }
    }
  }
]
